{
    "ChampionName": "Ornn",
    "ChangePatches": [
        "9.19",
        "10.5",
        "10.13",
        "10.15",
        "10.23",
        "12.10"
    ],
    "Changes": {
        "9.19": {
            "B": "",
            "P": {
                "SpellName": "Passive - Living Forge",
                "Changes": [
                    {
                        "Tag": "",
                        "Change": {
                            "Attribute": "MASTERWORK UPGRADE: ",
                            "Before": "13",
                            "Indicator": " ⇒ ",
                            "After": "12"
                        }
                    }
                ]
            },
            "Q": "",
            "W": "",
            "E": "",
            "R": ""
        },
        "10.5": {
            "B": "",
            "P": {
                "SpellName": "Passive - Living Forge",
                "Changes": [
                    {
                        "Tag": "",
                        "Change": {
                            "Attribute": "BRITTLE PROC DAMAGE: ",
                            "Before": "12-20.5% target's maximum health (level 1-18)",
                            "Indicator": " ⇒ ",
                            "After": "10-18% target's maximum health (level 1-18)"
                        }
                    },
                    {
                        "Tag": "",
                        "Change": {
                            "Attribute": "MASTERWORK ITEM AUTO-UPGRADE: ",
                            "Before": "Level 12",
                            "Indicator": " ⇒ ",
                            "After": "Level 13"
                        }
                    },
                    {
                        "Tag": "",
                        "Change": {
                            "Attribute": "ALLY MASTERWORK UPGRADE AVAILABILITY: ",
                            "Before": "Levels 13, 14, 15, 16",
                            "Indicator": " ⇒ ",
                            "After": "Levels 14, 15, 16, 17"
                        }
                    }
                ]
            },
            "Q": "",
            "W": "",
            "E": "",
            "R": ""
        },
        "10.13": {
            "B": "",
            "P": {
                "SpellName": "Passive - Living Forge",
                "Changes": [
                    {
                        "Tag": "",
                        "Change": {
                            "Attribute": "BACK TO BASICS: ",
                            "Before": "Health and mana items built in the field provide 100% of health and mana values",
                            "Indicator": " ⇒ ",
                            "After": "Health and mana items built in the field retain its previous health and mana percentage (returning to base still brings health and mana items back to full)"
                        }
                    }
                ]
            },
            "Q": "",
            "W": "",
            "E": "",
            "R": ""
        },
        "10.15": {
            "B": {
                "SpellName": "Base Stats",
                "Changes": [
                    {
                        "Tag": "",
                        "Change": {
                            "Attribute": "ARMOR: ",
                            "Before": "36",
                            "Indicator": " ⇒ ",
                            "After": "33"
                        }
                    }
                ]
            },
            "P": "",
            "Q": "",
            "W": "",
            "E": "",
            "R": ""
        },
        "10.23": {
            "B": "",
            "P": {
                "SpellName": "Passive - Living Forge",
                "Changes": [
                    {
                        "Tag": "",
                        "Change": {
                            "Attribute": "FORGEABLE ITEMS: ",
                            "Before": "Curated List",
                            "Indicator": " ⇒ ",
                            "After": "All Mythic items"
                        }
                    },
                    {
                        "Tag": "",
                        "Change": {
                            "Attribute": "MASTERWORK UPGRADE VALUE: ",
                            "Before": "Dependent on item",
                            "Indicator": " ⇒ ",
                            "After": "~1000 gold"
                        }
                    },
                    {
                        "Tag": "",
                        "Change": {
                            "Attribute": "MASTERWORK LIMIT: ",
                            "Before": "2 for Ornn, 1 for allies",
                            "Indicator": " ⇒ ",
                            "After": "1 for Ornn and allies (since Ornn is still subject to the 1 Mythic limit)"
                        }
                    },
                    {
                        "Tag": "",
                        "Change": {
                            "Attribute": "STAT BONUS: ",
                            "Before": "Ornn gains an additional 10% bonus armor and magic resistance",
                            "Indicator": " ⇒ ",
                            "After": "Ornn gains an additional 10% bonus health, armor, and magic resistance"
                        }
                    },
                    {
                        "Tag": "NEW",
                        "Change": {
                            "Attribute": "CALLOUSED HANDS: ",
                            "Before": "",
                            "Indicator": "",
                            "After": "Ornn gains an additional 4% bonus health, armor, and magic resistance for each Mythic item he upgrades into a Masterwork"
                        }
                    }
                ]
            },
            "Q": "",
            "W": "",
            "E": "",
            "R": ""
        },
        "12.10": {
            "B": {
                "SpellName": "Base Stats",
                "Changes": [
                    {
                        "Tag": "",
                        "Change": {
                            "Attribute": "BASE HEALTH: ",
                            "Before": "",
                            "Indicator": "",
                            "After": "+70"
                        }
                    },
                    {
                        "Tag": "",
                        "Change": {
                            "Attribute": "HEALTH GROWTH: ",
                            "Before": "",
                            "Indicator": "",
                            "After": "+14"
                        }
                    },
                    {
                        "Tag": "",
                        "Change": {
                            "Attribute": "ARMOR GROWTH: ",
                            "Before": "",
                            "Indicator": "",
                            "After": "+1.2"
                        }
                    },
                    {
                        "Tag": "",
                        "Change": {
                            "Attribute": "MAGIC RESIST GROWTH: ",
                            "Before": "",
                            "Indicator": "",
                            "After": " +0.8"
                        }
                    }
                ]
            },
            "P": "",
            "Q": "",
            "W": "",
            "E": "",
            "R": ""
        }
    },
    "stats": {
        "hp": {
            "base": 660,
            "increment": 109
        },
        "mp": {
            "base": 340.6,
            "increment": 65
        },
        "armor": {
            "base": 33,
            "increment": 5.2
        },
        "spellBlock": {
            "base": 32,
            "increment": 2.05
        },
        "hpRegen": {
            "base": 9,
            "increment": 0.9
        },
        "mpRegen": {
            "base": 8.01,
            "increment": 0.6
        },
        "attackSpeed": {
            "base": 0.625,
            "increment": 0.02
        },
        "ms": {
            "base": 335,
            "increment": 0
        },
        "attackDamage": {
            "base": 69,
            "increment": 3.5
        },
        "attackRange": {
            "base": 175,
            "increment": 0
        }
    },
    "spells": {
        "P": {
            "name": "Living Forge",
            "cooldown": "",
            "_rawTooltip": {
                "fullTooltip": "Innate: Ornn increases his bonus armo bonus magic resistance and bonus health by 10% from all sources, further increased by 4% each time he upgrades a Mythic item into a Masterwork item.<br>Innate - Living Forge: Ornn can purchase non-consumable items from anywhere on the field by forging them himself, and is also presented a Forge Menu with his recommended items to select to be forged. Forging takes 4 seconds and the process is interrupted if Ornn takes damage from enemy champions or turrets, disabling Living Forge for a few seconds. Gold is only expended upon completing the forge.<br>Innate - Master Craftsman: When Ornn reaches level 13, the Mythic item he owns or purchases is upgraded for free. Additionally, for each level after 13 (levels 14, 15, 16 and 17, excluding 18), Ornn can upgrade one of an allied champion's Mythic item by selecting them within 600 range. Each Masterwork item has roughly 1000-worth of additional stats.<br>Masterwork items:<br>Assassin: Draktharr's Shadowcarver, Sandshrike's Claw, Syzygy.<br>Fighter: Ceaseless Hunger, Deicide, Dreamshatter, Infinity Force.<br>Mage: Caesura, Eternal Winter, Eye of Luden, Icathia's Curse, Liandry's Lament, Upgraded Aeropack, Vespertide.<br>Marksman: Bloodward, Typhoon, Wyrmfallen Sacrifice.<br>Support: Equinox, Reliquary of the Golden Dawn, Seat of Command, Shurelya's Requiem, Starcaster.<br>Tank: Forgefire Crest, Rimeforged Grasp, Turbocharged Hexperiment.<br>Innate - Temper: Ornn's basic attacks against Brittle enemies knock them back a short distance.<br>Ornn's and allies' immobilizing effects against enemies afflicted by Brittle will consume the debuff to deal [[0]] as bonus magic damage, capped at 250 against monsters, and last 30% longer (if applicable).",
                "parseInfo": [
                    {
                        "text": {
                            "text": "10% − 18% {{0}} of the target's maximum health",
                            "scaleHolders": [
                                {
                                    "scale": "(based on Ornn's level)",
                                    "scaleId": "level"
                                }
                            ]
                        },
                        "type": "Health"
                    }
                ]
            }
        },
        "Q": {
            "id": "OrnnQ",
            "name": "Volcanic Rupture",
            "_rawTooltip": {
                "fullTooltip": "Ornn slams the ground, creating a fissure dealing [[0]] and [[1]] by 40% for 2 seconds. A pillar of rock forms at the fissure's end for 4 seconds. ",
                "parseInfo": [
                    {
                        "text": {
                            "text": "20/45/70/95/120 {{0}} physical damage",
                            "scaleHolders": [
                                {
                                    "scale": "(+110% AD)",
                                    "scaleId": "AD"
                                }
                            ]
                        },
                        "type": "physicalDamage"
                    },
                    {
                        "text": {
                            "text": "Slowing",
                            "scaleHolders": []
                        },
                        "type": "status"
                    }
                ]
            },
            "maxRank": 5,
            "cooldown": "9/8.5/8/7.5/7",
            "cooldownByLevel": [
                9,
                8.5,
                8,
                7.5,
                7
            ],
            "cost": "45 Mana",
            "costByLevel": [
                45,
                45,
                45,
                45,
                45
            ],
            "costType": " Mana"
        },
        "W": {
            "id": "OrnnW",
            "name": "Bellows Breath",
            "_rawTooltip": {
                "fullTooltip": "Ornn stomps forward Unstoppably while breathing fire, dealing [[0]] over 0.75 seconds. Enemies hit by the final bout of flame become [[1]] for 3 seconds.<br /><br />[[2]] effects on [[3]] targets have their duration increased by 30% and deal an additional [[4]]. Ornn's Attacks against [[5]] targets [[6]] them [[7]], dealing the additional damage.",
                "parseInfo": [
                    {
                        "text": {
                            "text": "12/13/14/15% max Health magic damage",
                            "scaleHolders": []
                        },
                        "type": "magicDamage"
                    },
                    {
                        "text": {
                            "text": "Brittle",
                            "scaleHolders": []
                        },
                        "type": ""
                    },
                    {
                        "text": {
                            "text": "Immobilizing",
                            "scaleHolders": []
                        },
                        "type": "status"
                    },
                    {
                        "text": {
                            "text": "Brittle",
                            "scaleHolders": []
                        },
                        "type": ""
                    },
                    {
                        "text": {
                            "text": "10% - 18% {{0}} max Health magic damage",
                            "scaleHolders": [
                                {
                                    "scale": "(based on champion level)",
                                    "scaleId": "level"
                                }
                            ]
                        },
                        "type": "magicDamage"
                    },
                    {
                        "text": {
                            "text": "Brittle",
                            "scaleHolders": []
                        },
                        "type": ""
                    },
                    {
                        "text": {
                            "text": "Knock",
                            "scaleHolders": []
                        },
                        "type": "status"
                    },
                    {
                        "text": {
                            "text": "Back",
                            "scaleHolders": []
                        },
                        "type": "status"
                    }
                ]
            },
            "maxRank": 5,
            "cooldown": "12/11.5/11/10.5/10",
            "cooldownByLevel": [
                12,
                11.5,
                11,
                10.5,
                10
            ],
            "cost": "45/50/55/60/65 Mana",
            "costByLevel": [
                45,
                50,
                55,
                60,
                65
            ],
            "costType": " Mana"
        },
        "E": {
            "id": "OrnnE",
            "name": "Searing Charge",
            "_rawTooltip": {
                "fullTooltip": "Ornn charges, dealing [[0]]. If Ornn rams into terrain, he creates a shockwave that [[1]] enemies for 1.25 seconds and applies the same damage to those not hit by the charge.<br /><br />Ornn's charge destroys magma pillars and terrain created by enemies.",
                "parseInfo": [
                    {
                        "text": {
                            "text": "80/125/170/215/260 {{0}} {{1}} physical damage",
                            "scaleHolders": [
                                {
                                    "scale": "(+40% Bonus Armor)",
                                    "scaleId": "Armor"
                                },
                                {
                                    "scale": "(+40% Bonus MR)",
                                    "scaleId": "MR"
                                }
                            ]
                        },
                        "type": "physicalDamage"
                    },
                    {
                        "text": {
                            "text": "Knocks Up",
                            "scaleHolders": []
                        },
                        "type": "status"
                    }
                ]
            },
            "maxRank": 5,
            "cooldown": "16/15/14/13/12",
            "cooldownByLevel": [
                16,
                15,
                14,
                13,
                12
            ],
            "cost": "35/40/45/50/55 Mana",
            "costByLevel": [
                35,
                40,
                45,
                50,
                55
            ],
            "costType": " Mana"
        },
        "R": {
            "id": "OrnnR",
            "name": "Call of the Forge God",
            "_rawTooltip": {
                "fullTooltip": "Ornn summons a massive lava elemental, which stampedes towards him, dealing [[0]], and applying [[1]] for 3 seconds. The elemental also [[2]] by up to 40/50% based on distance traveled.<br /><br />Ornn can [[3]] to dash with a headbutt. If he dashes into the elemental, he redirects and empowers it, causing it to [[4]] the first champion for 1 second and subsequent champions for 0.5 seconds. The elemental also deals [[5]] and reapplies [[6]].",
                "parseInfo": [
                    {
                        "text": {
                            "text": "125/175/225 {{0}} magic damage",
                            "scaleHolders": [
                                {
                                    "scale": "(+20% AP)",
                                    "scaleId": "AP"
                                }
                            ]
                        },
                        "type": "magicDamage"
                    },
                    {
                        "text": {
                            "text": "Brittle",
                            "scaleHolders": []
                        },
                        "type": ""
                    },
                    {
                        "text": {
                            "text": "Slows",
                            "scaleHolders": []
                        },
                        "type": "status"
                    },
                    {
                        "text": {
                            "text": "Recast",
                            "scaleHolders": []
                        },
                        "type": ""
                    },
                    {
                        "text": {
                            "text": "Knock Up",
                            "scaleHolders": []
                        },
                        "type": "status"
                    },
                    {
                        "text": {
                            "text": "125/175/225 {{0}} magic damage",
                            "scaleHolders": [
                                {
                                    "scale": "(+20% AP)",
                                    "scaleId": "AP"
                                }
                            ]
                        },
                        "type": "magicDamage"
                    },
                    {
                        "text": {
                            "text": "Brittle",
                            "scaleHolders": []
                        },
                        "type": ""
                    }
                ]
            },
            "maxRank": 3,
            "cooldown": "140/120/100",
            "cooldownByLevel": [
                140,
                120,
                100
            ],
            "cost": "100 Mana",
            "costByLevel": [
                100,
                100,
                100
            ],
            "costType": " Mana"
        }
    }
}